Workbook

Sheet Mutual Fund Specifics
F3: Fund Name | G3: Aditya Birla Sun Life Flexi Cap Fund Direct Growth
F4: Benchmark | G4: NIFTY 500 TRI
F5: No of Stocks | G5: 81
F6: Average Market Cap | G6: Rs 170397.25 Cr
F7: Expense Ratio | G7: 0.0165
F8: Fund Managers | G8: Dhaval Joshi, Harish Krishnan
F18: Holdings Taken (Top 5, does not include SBI)
G33: (from money control)
F36: Riskometer and Fund Managers
G52: (from money control)

Sheet Closing Prices
D4: Closing Price of Each Asset has been taken from the NSE Website
D6: Day | E6: Date | F6: ICICI Bank | G6: HDFC Bank | H6: Kotak Mahindra Bank | I6: Infosys Ltd | J6: Reliance Industries Ltd | K6: NIFTY 50
D7: 1 | E7: 46101 | F7: 1245.4 | G7: 780.45 | H7: 375.4 | I7: 1256.8 | J7: 1384.8 | K7: 21327.9
D8: 2 | E8: 46100 | F8: 1250.1 | G8: 798.2 | H8: 374.2 | I8: 1255.9 | J8: 1408.1 | K8: 21225.8
D9: 3 | E9: 46099 | F9: 1289.3 | G9: 843.05 | H9: 369.85 | I9: 1220.8 | J9: 1397.6 | K9: 21917.4
D10: 4 | E10: 46098 | F10: 1288.7 | G10: 845.35 | H10: 366.85 | I10: 1267.1 | J10: 1395.1 | K10: 21669.3
D11: 5 | E11: 46097 | F11: 1272.9 | G11: 840.6 | H11: 375.3 | I11: 1232.9 | J11: 1380.7 | K11: 21498.8
D12: 6 | E12: 46094 | F12: 1254.8 | G12: 817 | H12: 383.2 | I12: 1249.8 | J12: 1392.2 | K12: 21391.2
D13: 7 | E13: 46093 | F13: 1266.5 | G13: 832.75 | H13: 391.85 | I13: 1248.3 | J13: 1390.2 | K13: 21897.5
D14: 8 | E14: 46092 | F14: 1294.6 | G14: 833.95 | H14: 386.35 | I14: 1265.8 | J14: 1408.8 | K14: 22042.3
D15: 9 | E15: 46091 | F15: 1311.9 | G15: 849.45 | H15: 399.8 | I15: 1276.3 | J15: 1424 | K15: 22342.95
D16: 10 | E16: 46090 | F16: 1278.4 | G16: 840.7 | H16: 407.3 | I16: 1295.6 | J16: 1404.8 | K16: 22056.55
D17: 11 | E17: 46087 | F17: 1313.4 | G17: 857.05 | H17: 403.35 | I17: 1315 | J17: 1389.4 | K17: 22481.3
D18: 12 | E18: 46086 | F18: 1357.6 | G18: 868.65 | H18: 413.1 | I18: 1308.4 | J18: 1345 | K18: 22697.8
... D259: 253 | E259: 45740 | F259: 1358.15 | G259: 1800 | H259: 2176.15 | I259: 1592.75 | J259: 1302.1 | K259: 21055.6

Sheet Returns Calculation
D4: To check the calculation of the return values Refer to the Covariance variance Sheet, The Values have been copied from thhere
D8: Days | E8: ICICI Bank | F8: HDFC Bank | G8: Kotak Mahindra Bank | H8: Infosys Ltd | I8: Reliance Industries Ltd | J8: Nifty 50
D9: 1 | E9: =LN('Closing Prices'!F8/'Closing Prices'!F7) -> 0.0037667847 | F9: =LN('Closing Prices'!G8/'Closing Prices'!G7) -> 0.022488516 | G9: =LN('Closing Prices'!H8/'Closing Prices'!H7) -> -0.0032017103 | H9: =LN('Closing Prices'!I8/'Closing Prices'!I7) -> -0.00071636092 | I9: =LN('Closing Prices'!J8/'Closing Prices'!J7) -> 0.016685553 | J9: =LN('Closing Prices'!K8/'Closing Prices'!K7) -> -0.0047986519
D10: 2 | E10: =LN('Closing Prices'!F9/'Closing Prices'!F8) -> 0.030875887 | F10: =LN('Closing Prices'!G9/'Closing Prices'!G8) -> 0.054667076 | G10: =LN('Closing Prices'!H9/'Closing Prices'!H8) -> -0.011692896 | H10: =LN('Closing Prices'!I9/'Closing Prices'!I8) -> -0.028346065 | I10: =LN('Closing Prices'!J9/'Closing Prices'!J8) -> -0.0074847981 | J10: =LN('Closing Prices'!K9/'Closing Prices'!K8) -> 0.032063419
D11: 3 | E11: =LN('Closing Prices'!F10/'Closing Prices'!F9) -> -0.00046547712 | F11: =LN('Closing Prices'!G10/'Closing Prices'!G9) -> 0.0027244746 | G11: =LN('Closing Prices'!H10/'Closing Prices'!H9) -> -0.0081444729 | H11: =LN('Closing Prices'!I10/'Closing Prices'!I9) -> 0.037224443 | I11: =LN('Closing Prices'!J10/'Closing Prices'!J9) -> -0.0017903825 | J11: =LN('Closing Prices'!K10/'Closing Prices'!K9) -> -0.01138433
D12: 4 | E12: =LN('Closing Prices'!F11/'Closing Prices'!F10) -> -0.012336196 | F12: =LN('Closing Prices'!G11/'Closing Prices'!G10) -> -0.0056348202 | G12: =LN('Closing Prices'!H11/'Closing Prices'!H10) -> 0.022772661 | H12: =LN('Closing Prices'!I11/'Closing Prices'!I10) -> -0.027361707 | I12: =LN('Closing Prices'!J11/'Closing Prices'!J10) -> -0.01037548 | J12: =LN('Closing Prices'!K11/'Closing Prices'!K10) -> -0.0078993927
D13: 5 | E13: =LN('Closing Prices'!F12/'Closing Prices'!F11) -> -0.014321565 | F13: =LN('Closing Prices'!G12/'Closing Prices'!G11) -> -0.028476828 | G13: =LN('Closing Prices'!H12/'Closing Prices'!H11) -> 0.02083134 | H13: =LN('Closing Prices'!I12/'Closing Prices'!I11) -> 0.013614421 | I13: =LN('Closing Prices'!J12/'Closing Prices'!J11) -> 0.0082946128 | J13: =LN('Closing Prices'!K12/'Closing Prices'!K11) -> -0.0050174971
D14: 6 | E14: =LN('Closing Prices'!F13/'Closing Prices'!F12) -> 0.0092809931 | F14: =LN('Closing Prices'!G13/'Closing Prices'!G12) -> 0.019094382 | G14: =LN('Closing Prices'!H13/'Closing Prices'!H12) -> 0.022322067 | H14: =LN('Closing Prices'!I13/'Closing Prices'!I12) -> -0.0012009128 | I14: =LN('Closing Prices'!J13/'Closing Prices'!J12) -> -0.0014376081 | J14: =LN('Closing Prices'!K13/'Closing Prices'!K12) -> 0.023392853
D15: 7 | E15: =LN('Closing Prices'!F14/'Closing Prices'!F13) -> 0.021944577 | F15: =LN('Closing Prices'!G14/'Closing Prices'!G13) -> 0.0014399714 | G15: =LN('Closing Prices'!H14/'Closing Prices'!H13) -> -0.014135419 | H15: =LN('Closing Prices'!I14/'Closing Prices'!I13) -> 0.013921708 | I15: =LN('Closing Prices'!J14/'Closing Prices'!J13) -> 0.013290657 | J15: =LN('Closing Prices'!K14/'Closing Prices'!K13) -> 0.0065908595
D16: 8 | E16: =LN('Closing Prices'!F15/'Closing Prices'!F14) -> 0.013274701 | F16: =LN('Closing Prices'!G15/'Closing Prices'!G14) -> 0.018415633 | G16: =LN('Closing Prices'!H15/'Closing Prices'!H14) -> 0.034220728 | H16: =LN('Closing Prices'!I15/'Closing Prices'!I14) -> 0.0082609336 | I16: =LN('Closing Prices'!J15/'Closing Prices'!J14) -> 0.010731535 | J16: =LN('Closing Prices'!K15/'Closing Prices'!K14) -> 0.013547501
D17: 9 | E17: =LN('Closing Prices'!F16/'Closing Prices'!F15) -> -0.025867172 | F17: =LN('Closing Prices'!G16/'Closing Prices'!G15) -> -0.010354203 | G17: =LN('Closing Prices'!H16/'Closing Prices'!H15) -> 0.018585593 | H17: =LN('Closing Prices'!I16/'Closing Prices'!I15) -> 0.015008641 | I17: =LN('Closing Prices'!J16/'Closing Prices'!J15) -> -0.013574869 | J17: =LN('Closing Prices'!K16/'Closing Prices'!K15) -> -0.012901225
D18: 10 | E18: =LN('Closing Prices'!F17/'Closing Prices'!F16) -> 0.027009899 | F18: =LN('Closing Prices'!G17/'Closing Prices'!G16) -> 0.019261382 | G18: =LN('Closing Prices'!H17/'Closing Prices'!H16) -> -0.0097453433 | H18: =LN('Closing Prices'!I17/'Closing Prices'!I16) -> 0.014862757 | I18: =LN('Closing Prices'!J17/'Closing Prices'!J16) -> -0.011022945 | J18: =LN('Closing Prices'!K17/'Closing Prices'!K16) -> 0.019074243
D19: 11 | E19: =LN('Closing Prices'!F18/'Closing Prices'!F17) -> 0.03309924 | F19: =LN('Closing Prices'!G18/'Closing Prices'!G17) -> 0.013444022 | G19: =LN('Closing Prices'!H18/'Closing Prices'!H17) -> 0.023885023 | H19: =LN('Closing Prices'!I18/'Closing Prices'!I17) -> -0.0050316489 | I19: =LN('Closing Prices'!J18/'Closing Prices'!J17) -> -0.032477986 | J19: =LN('Closing Prices'!K18/'Closing Prices'!K17) -> 0.009584151
D20: 12 | E20: =LN('Closing Prices'!F19/'Closing Prices'!F18) -> 0.0057289911 | F20: =LN('Closing Prices'!G19/'Closing Prices'!G18) -> 0.010421533 | G20: =LN('Closing Prices'!H19/'Closing Prices'!H18) -> 0.0050706374 | H20: =LN('Closing Prices'!I19/'Closing Prices'!I18) -> -0.0019891369 | I20: =LN('Closing Prices'!J19/'Closing Prices'!J18) -> 0.0096190161 | J20: =LN('Closing Prices'!K19/'Closing Prices'!K18) -> -0.01276964
... D260: 252 | E260: =LN('Closing Prices'!F259/'Closing Prices'!F258) -> 0.010696477 | F260: =LN('Closing Prices'!G259/'Closing Prices'!G258) -> -0.011846222 | G260: =LN('Closing Prices'!H259/'Closing Prices'!H258) -> 0.0028300929 | H260: =LN('Closing Prices'!I259/'Closing Prices'!I258) -> -0.02216656 | I260: =LN('Closing Prices'!J259/'Closing Prices'!J258) -> 0.012869494 | J260: =LN('Closing Prices'!K259/'Closing Prices'!K258) -> -0.00046532609

Sheet Covariance Variance Matrix 
L4: Average | M4: =AVERAGE(M11:M262) -> 0.00034391554 | N4: =AVERAGE(N11:N262) -> 0.0033161558 | O4: =AVERAGE(O11:O262) -> 0.0069734937 | P4: =AVERAGE(P11:P262) -> 0.00094005267 | Q4: =AVERAGE(Q11:Q262) -> -0.00024435468
L5: Variance | M5: =_xlfn.VAR.S(M11:M262) -> 0.00012213829 | N5: =_xlfn.VAR.S(N11:N262) -> 0.0020608986 | O5: =_xlfn.VAR.S(O11:O262) -> 0.010609484 | P5: =_xlfn.VAR.S(P11:P262) -> 0.00027018941 | Q5: =_xlfn.VAR.S(Q11:Q262) -> 0.00016386129
L6: Standard Deviation | M6: =SQRT(M5) -> 0.011051619 | N6: =SQRT(N5) -> 0.045397121 | O6: =SQRT(O5) -> 0.10300235 | P6: =SQRT(P5) -> 0.016437439 | Q6: =SQRT(Q5) -> 0.012800832
C8: Raw Data
L9: Returns Calculation | X9: Covariance-Variance Matrix
C10: Day | D10: Date | E10: ICICI Bank | F10: HDFC Bank | G10: Kotak Mahindra Bank | H10: Infosys Ltd | I10: Reliance Industries Ltd | J10: NIFTY 50 | L10: Date | M10: ICICI Bank | N10: HDFC Bank | O10: Kotak Mahindra Bank | P10: Infosys Ltd | Q10: Reliance Industries Ltd
C11: 1 | D11: 46101 | E11: 1245.4 | F11: 780.45 | G11: 375.4 | H11: 1256.8 | I11: 1384.8 | J11: 21327.9 | L11: 1 | M11: =LN(E12/E11) -> 0.0037667847 | N11: =LN(F12/F11) -> 0.022488516 | O11: =LN(G12/G11) -> -0.0032017103 | P11: =LN(H12/H11) -> -0.00071636092 | Q11: =LN(I12/I11) -> 0.016685553 | AA11: ICICI Bank | AB11: HDFC Bank | AC11: Kotak Mahindra Bank | AD11: Infosys Ltd | AE11: Reliance Industries Ltd
C12: 2 | D12: 46100 | E12: 1250.1 | F12: 798.2 | G12: 374.2 | H12: 1255.9 | I12: 1408.1 | J12: 21225.8 | L12: 2 | M12: =LN(E13/E12) -> 0.030875887 | N12: =LN(F13/F12) -> 0.054667076 | O12: =LN(G13/G12) -> -0.011692896 | P12: =LN(H13/H12) -> -0.028346065 | Q12: =LN(I13/I12) -> -0.0074847981 | Y12: Averages | AA12: 0.2 | AB12: 0.2 | AC12: 0.2 | AD12: 0.2 | AE12: 0.2
C13: 3 | D13: 46099 | E13: 1289.3 | F13: 843.05 | G13: 369.85 | H13: 1220.8 | I13: 1397.6 | J13: 21917.4 | L13: 3 | M13: =LN(E14/E13) -> -0.00046547712 | N13: =LN(F14/F13) -> 0.0027244746 | O13: =LN(G14/G13) -> -0.0081444729 | P13: =LN(H14/H13) -> 0.037224443 | Q13: =LN(I14/I13) -> -0.0017903825 | X13: ICICI Bank | Y13: =M4 -> 0.00034391554 | Z13: 0.2 | AA13: {=MMULT(TRANSPOSE(M11:Q262),M11:Q262)/252} -> 0.00012177189 | AB13: 8.1525655e-05 | AC13: 0.00015502937 | AD13: 2.0698241e-05 | AE13: 3.5629546e-05
C14: 4 | D14: 46098 | E14: 1288.7 | F14: 845.35 | G14: 366.85 | H14: 1267.1 | I14: 1395.1 | J14: 21669.3 | L14: 4 | M14: =LN(E15/E14) -> -0.012336196 | N14: =LN(F15/F14) -> -0.0056348202 | O14: =LN(G15/G14) -> 0.022772661 | P14: =LN(H15/H14) -> -0.027361707 | Q14: =LN(I15/I14) -> -0.01037548 | X14: HDFC Bank | Y14: =N4 -> 0.0033161558 | Z14: 0.2 | AA14: 8.1525655e-05 | AB14: 0.0020637173 | AC14: 2.6388553e-05 | AD14: 8.0076129e-05 | AE14: 8.5259813e-05
C15: 5 | D15: 46097 | E15: 1272.9 | F15: 840.6 | G15: 375.3 | H15: 1232.9 | I15: 1380.7 | J15: 21498.8 | L15: 5 | M15: =LN(E16/E15) -> -0.014321565 | N15: =LN(F16/F15) -> -0.028476828 | O15: =LN(G16/G15) -> 0.02083134 | P15: =LN(H16/H15) -> 0.013614421 | Q15: =LN(I16/I15) -> 0.0082946128 | X15: Kotak Mahindra Bank | Y15: =O4 -> 0.0069734937 | Z15: 0.2 | AA15: 0.00015502937 | AB15: 2.6388553e-05 | AC15: 0.010616013 | AD15: 0.00010420491 | AE15: 2.408939e-05
C16: 6 | D16: 46094 | E16: 1254.8 | F16: 817 | G16: 383.2 | H16: 1249.8 | I16: 1392.2 | J16: 21391.2 | L16: 6 | M16: =LN(E17/E16) -> 0.0092809931 | N16: =LN(F17/F16) -> 0.019094382 | O16: =LN(G17/G16) -> 0.022322067 | P16: =LN(H17/H16) -> -0.0012009128 | Q16: =LN(I17/I16) -> -0.0014376081 | X16: Infosys Ltd | Y16: =P4 -> 0.00094005267 | Z16: 0.2 | AA16: 2.0698241e-05 | AB16: 8.0076129e-05 | AC16: 0.00010420491 | AD16: 0.00027000093 | AE16: 3.3386573e-05
C17: 7 | D17: 46093 | E17: 1266.5 | F17: 832.75 | G17: 391.85 | H17: 1248.3 | I17: 1390.2 | J17: 21897.5 | L17: 7 | M17: =LN(E18/E17) -> 0.021944577 | N17: =LN(F18/F17) -> 0.0014399714 | O17: =LN(G18/G17) -> -0.014135419 | P17: =LN(H18/H17) -> 0.013921708 | Q17: =LN(I18/I17) -> 0.013290657 | X17: Reliance Industries Ltd | Y17: =Q4 -> -0.00024435468 | Z17: 0.2 | AA17: 3.5629546e-05 | AB17: 8.5259813e-05 | AC17: 2.408939e-05 | AD17: 3.3386573e-05 | AE17: 0.00016327076
C18: 8 | D18: 46092 | E18: 1294.6 | F18: 833.95 | G18: 386.35 | H18: 1265.8 | I18: 1408.8 | J18: 22042.3 | L18: 8 | M18: =LN(E19/E18) -> 0.013274701 | N18: =LN(F19/F18) -> 0.018415633 | O18: =LN(G19/G18) -> 0.034220728 | P18: =LN(H19/H18) -> 0.0082609336 | Q18: =LN(I19/I18) -> 0.010731535
C19: 9 | D19: 46091 | E19: 1311.9 | F19: 849.45 | G19: 399.8 | H19: 1276.3 | I19: 1424 | J19: 22342.95 | L19: 9 | M19: =LN(E20/E19) -> -0.025867172 | N19: =LN(F20/F19) -> -0.010354203 | O19: =LN(G20/G19) -> 0.018585593 | P19: =LN(H20/H19) -> 0.015008641 | Q19: =LN(I20/I19) -> -0.013574869
C20: 10 | D20: 46090 | E20: 1278.4 | F20: 840.7 | G20: 407.3 | H20: 1295.6 | I20: 1404.8 | J20: 22056.55 | L20: 10 | M20: =LN(E21/E20) -> 0.027009899 | N20: =LN(F21/F20) -> 0.019261382 | O20: =LN(G21/G20) -> -0.0097453433 | P20: =LN(H21/H20) -> 0.014862757 | Q20: =LN(I21/I20) -> -0.011022945
C21: 11 | D21: 46087 | E21: 1313.4 | F21: 857.05 | G21: 403.35 | H21: 1315 | I21: 1389.4 | J21: 22481.3 | L21: 11 | M21: =LN(E22/E21) -> 0.03309924 | N21: =LN(F22/F21) -> 0.013444022 | O21: =LN(G22/G21) -> 0.023885023 | P21: =LN(H22/H21) -> -0.0050316489 | Q21: =LN(I22/I21) -> -0.032477986 | Y21: Portfolio Return | Z21: =SUMPRODUCT(Y13:Y17,Z13:Z17) -> 0.0022658526
C22: 12 | D22: 46086 | E22: 1357.6 | F22: 868.65 | G22: 413.1 | H22: 1308.4 | I22: 1345 | J22: 22697.8 | L22: 12 | M22: =LN(E23/E22) -> 0.0057289911 | N22: =LN(F23/F22) -> 0.010421533 | O22: =LN(G23/G22) -> 0.0050706374 | P22: =LN(H23/H22) -> -0.0019891369 | Q22: =LN(I23/I22) -> 0.0096190161 | Y22: Variance of Portfolio | Z22: {=MMULT(TRANSPOSE(Z13:Z17),MMULT(AA13:AE17,Z13:Z17))} -> 0.000581094
C23: 13 | D23: 46085 | E23: 1365.4 | F23: 877.75 | G23: 415.2 | H23: 1305.8 | I23: 1358 | J23: 22409.8 | L23: 13 | M23: =LN(E24/E23) -> 0.0062787678 | N23: =LN(F24/F23) -> -0.010421533 | O23: =LN(G24/G23) -> 0.022269453 | P23: =LN(H24/H23) -> 0.0012245524 | Q23: =LN(I24/I23) -> 0.026092545 | Y23: Portoflio Daily SD | Z23: =SQRT(Z22) -> 0.024105891
C24: 14 | D24: 46083 | E24: 1374 | F24: 868.65 | G24: 424.55 | H24: 1307.4 | I24: 1393.9 | J24: 22835.95 | L24: 14 | M24: =LN(E25/E24) -> 0.0035598861 | N24: =LN(F25/F24) -> 0.012299574 | O24: =LN(G25/G24) -> 0.0009417305 | P24: =LN(H25/H24) -> -0.014251291 | Q24: =LN(I25/I24) -> 0.0092120479 | Y24: Annual SD | Z24: {=Z23*SQRT(252)} -> 0.38266916
C25: 15 | D25: 46080 | E25: 1378.9 | F25: 879.4 | G25: 424.95 | H25: 1288.9 | I25: 1406.8 | J25: 23166.85 | L25: 15 | M25: =LN(E26/E25) -> 0.018680046 | N25: =LN(F26/F25) -> 0.0094503151 | O25: =LN(G26/G25) -> 0.0064505003 | P25: =LN(H26/H25) -> 0.0086520432 | Q25: =LN(I26/I25) -> -0.005917388
C26: 16 | D26: 46079 | E26: 1404.9 | F26: 887.75 | G26: 427.7 | H26: 1300.1 | I26: 1398.5 | J26: 23448.5 | L26: 16 | M26: =LN(E27/E26) -> -0.0031368102 | N26: =LN(F27/F26) -> 0.012147825 | O26: =LN(G27/G26) -> 0.0069897768 | P26: =LN(H27/H26) -> -0.0084968841 | Q26: =LN(I27/I26) -> 0.021434697
C27: 17 | D27: 46078 | E27: 1400.5 | F27: 898.6 | G27: 430.7 | H27: 1289.1 | I27: 1428.8 | J27: 23403.8 | L27: 17 | M27: =LN(E28/E27) -> -0.011273591 | N27: =LN(F28/F27) -> 0.0099657563 | O27: =LN(G28/G27) -> -0.02194795 | P27: =LN(H28/H27) -> 0.00077543428 | Q27: =LN(I28/I27) -> -0.00056006722
C28: 18 | D28: 46077 | E28: 1384.8 | F28: 907.6 | G28: 421.35 | H28: 1290.1 | I28: 1428 | J28: 23304.6 | L28: 18 | M28: =LN(E29/E28) -> 0.010487848 | N28: =LN(F29/F28) -> 0.0031901463 | O28: =LN(G29/G28) -> -0.011817505 | P28: =LN(H29/H28) -> -0.011381476 | Q28: =LN(I29/I28) -> -0.0060406168
C29: 19 | D29: 46076 | E29: 1399.4 | F29: 910.5 | G29: 416.4 | H29: 1275.5 | I29: 1419.4 | J29: 23484.95 | L29: 19 | M29: =LN(E30/E29) -> -0.0035076452 | N29: =LN(F30/F29) -> 0.014285178 | O29: =LN(G30/G29) -> 0.023614268 | P29: =LN(H30/H29) -> 0.039959216 | Q29: =LN(I30/I29) -> -0.0069992155
C30: 20 | D30: 46073 | E30: 1394.5 | F30: 923.6 | G30: 426.35 | H30: 1327.5 | I30: 1409.5 | J30: 23395 | L30: 20 | M30: =LN(E31/E30) -> -0.0040958632 | N30: =LN(F31/F30) -> -0.012803575 | O30: =LN(G31/G30) -> -0.004466392 | P30: =LN(H31/H30) -> 0.019174684 | Q30: =LN(I31/I30) -> 0.022310453
C31: 21 | D31: 46072 | E31: 1388.8 | F31: 911.85 | G31: 424.45 | H31: 1353.2 | I31: 1441.3 | J31: 23297.45 | L31: 21 | M31: =LN(E32/E31) -> 0.013872228 | N31: =LN(F32/F31) -> 0.0041040852 | O31: =LN(G32/G31) -> 0.0027057248 | P31: =LN(H32/H31) -> 0.012703479 | Q31: =LN(I32/I31) -> -0.012778165
C32: 22 | D32: 46071 | E32: 1408.2 | F32: 915.6 | G32: 425.6 | H32: 1370.5 | I32: 1423 | J32: 23645.8 | L32: 22 | M32: =LN(E33/E32) -> -0.00049721207 | N32: =LN(F33/F32) -> 0.0098897725 | O32: =LN(G33/G32) -> -0.011698804 | P32: =LN(H33/H32) -> 0.0023321926 | Q32: =LN(I33/I32) -> 0.009859875
C33: 23 | D33: 46070 | E33: 1407.5 | F33: 924.7 | G33: 420.65 | H33: 1373.7 | I33: 1437.1 | J33: 23540.05 | L33: 23 | M33: =LN(E34/E33) -> 0.0029087318 | N33: =LN(F34/F33) -> 0.0010808475 | O33: =LN(G34/G33) -> 0.013224895 | P33: =LN(H34/H33) -> 0.012658855 | Q33: =LN(I34/I33) -> -0.012252052
C34: 24 | D34: 46069 | E34: 1411.6 | F34: 925.7 | G34: 426.25 | H34: 1391.2 | I34: 1419.6 | J34: 23472.45 | L34: 24 | M34: =LN(E35/E34) -> 0.0021229928 | N34: =LN(F35/F34) -> 0.00010802052 | O34: =LN(G35/G34) -> 0.0077121205 | P34: =LN(H35/H34) -> -0.018572792 | Q34: =LN(I35/I34) -> 0.020429506
C35: 25 | D35: 46066 | E35: 1414.6 | F35: 925.8 | G35: 429.55 | H35: 1365.6 | I35: 1448.9 | J35: 23313.15 | L35: 25 | M35: =LN(E36/E35) -> 0.010827639 | N35: =LN(F36/F35) -> -0.023939494 | O35: =LN(G36/G35) -> -0.00058217385 | P35: =LN(H36/H35) -> 0.0025596972 | Q35: =LN(I36/I35) -> 0.013573008
C36: 26 | D36: 46065 | E36: 1430 | F36: 903.9 | G36: 429.3 | H36: 1369.1 | I36: 1468.7 | J36: 23651.55 | L36: 26 | M36: =LN(E37/E36) -> -0.01685453 | N36: =LN(F37/F36) -> 0.018306897 | O36: =LN(G37/G36) -> -0.0011653655 | P36: =LN(H37/H36) -> 0.012268311 | Q36: =LN(I37/I36) -> -0.0069691455
... C262: 252 | D262: 45741 | E262: 1343.7 | F262: 1821.45 | G262: 2170 | H262: 1628.45 | I262: 1285.45 | J262: 21065.4 | L262: 252 | M262: =LN(E263/E262) -> 0.010696477 | N262: =LN(F263/F262) -> -0.011846222 | O262: =LN(G263/G262) -> 0.0028300929 | P262: =LN(H263/H262) -> -0.02216656 | Q262: =LN(I263/I262) -> 0.012869494
C263: 253 | D263: 45740 | E263: 1358.15 | F263: 1800 | G263: 2176.15 | H263: 1592.75 | I263: 1302.1 | J263: 21055.6

Sheet VaR With Equal Weights
C6: VaR with Equal Weightage
C7: All Values are in percentage
C8: 95% 1-day VaR | D8: =100*_xlfn.NORM.S.INV(95%)*'Covariance Variance Matrix '!Z23 -> 3.9650663
C9: 95% 1-year VaR | D9: =100*_xlfn.NORM.S.INV(95%)*'Covariance Variance Matrix '!Z24 -> 62.943476
C10: 99% 1-day VaR | D10: =100*_xlfn.NORM.S.INV(99%)*'Covariance Variance Matrix '!Z23 -> 5.6078689
C11: 99% 1-year VaR | D11: =100*_xlfn.NORM.S.INV(99%)*'Covariance Variance Matrix '!Z24 -> 89.022159

Sheet VaR with Optimized Weights 
I3: ICICI Bank | J3: HDFC Bank | K3: Kotak Mahindra Bank | L3: Infosys Ltd | M3: Reliance Industries Ltd
C4: Stocks | D4: Returns | E4: Weights | I4: =H5 -> 0.6 | J4: =H6 -> 0.1 | K4: =H7 -> 0.1 | L4: =H8 -> 0.1 | M4: =H9 -> 0.1
C5: ICICI Bank | D5: 0.00034391554 | E5: 0.6 | G5: ICICI Bank | H5: =E5 -> 0.6 | I5: 0.00012177189 | J5: 8.1525655e-05 | K5: 0.00015502937 | L5: 2.0698241e-05 | M5: 3.5629546e-05
C6: HDFC Bank | D6: 0.0033161558 | E6: 0.1 | G6: HDFC Bank | H6: =E6 -> 0.1 | I6: 8.1525655e-05 | J6: 0.0020637173 | K6: 2.6388553e-05 | L6: 8.0076129e-05 | M6: 8.5259813e-05
C7: Kotak Mahindra Bank | D7: 0.0069734937 | E7: 0.1 | G7: Kotak Mahindra Bank | H7: =E7 -> 0.1 | I7: 0.00015502937 | J7: 2.6388553e-05 | K7: 0.010616013 | L7: 0.00010420491 | M7: 2.408939e-05
C8: Infosys Ltd | D8: 0.00094005267 | E8: 0.1 | G8: Infosys Ltd | H8: =E8 -> 0.1 | I8: 2.0698241e-05 | J8: 8.0076129e-05 | K8: 0.00010420491 | L8: 0.00027000093 | M8: 3.3386573e-05
C9: Reliance Industries Ltd | D9: -0.00024435468 | E9: 0.1 | G9: Reliance Industries Ltd | H9: =E9 -> 0.1 | I9: 3.5629546e-05 | J9: 8.5259813e-05 | K9: 2.408939e-05 | L9: 3.3386573e-05 | M9: 0.00016327076
E10: =SUM(E5:E9) -> 1
C12: Portfolio Return | D12: {=SUMPRODUCT(D5:D9,E5:E9)} -> 0.0013048841
C13: Portfolio Variance | D13: {=MMULT(TRANSPOSE(H5:H9),MMULT(I5:M9,H5:H9))} -> 0.00021718194
C14: Portfolio Daily SD | D14: =SQRT(D13) -> 0.014737094
C15: Annual SD | D15: =D14*SQRT(252) -> 0.23394412
C17: 95% 1 day VaR | D17: =100*_xlfn.NORM.S.INV(95%)*$D$14 -> 2.4240363
C18: 95% 1 year VaR | D18: =100*_xlfn.NORM.S.INV(95%)*$D$15 -> 38.480383
C19: 99% 1 day VaR | D19: =100*_xlfn.NORM.S.INV(99%)*$D$14 -> 3.4283608
C20: 99% 1 year VaR | D20: =100*_xlfn.NORM.S.INV(99%)*$D$15 -> 54.42354

Sheet Ratio's
F2: RATIOS
D3: ICICI Bank | E3: HDFC Bank | F3: Kotak Mahindra Bank | G3: Infosys Ltd | H3: Reliance Industries Ltd
C4: BETA | D4: =SLOPE('Returns Calculation'!E9:E260,'Returns Calculation'!$J$9:$J$260) -> 0.21871994 | E4: =SLOPE('Returns Calculation'!F9:F260,'Returns Calculation'!$J$9:$J$260) -> -0.14302527 | F4: =SLOPE('Returns Calculation'!G9:G260,'Returns Calculation'!$J$9:$J$260) -> 0.41800927 | G4: =SLOPE('Returns Calculation'!H9:H260,'Returns Calculation'!$J$9:$J$260) -> 0.014151514 | H4: =SLOPE('Returns Calculation'!I9:I260,'Returns Calculation'!$J$9:$J$260) -> 0.1256433
C5: Optimised Weights | D5: 0.6 | E5: 0.1 | F5: 0.1 | G5: 0.1 | H5: 0.1
C6: Equal Weights | D6: 0.2 | E6: 0.2 | F6: 0.2 | G6: 0.2 | H6: 0.2
C7: Portfolio Beta | D7: =SUMPRODUCT(D4:H4,D5:H5) -> 0.17270984 | E7: (optimised weights
D8: =SUMPRODUCT(D6:H6,D4:H4) -> 0.12669975 | E8: Equal weights
C9: Risk Free Rate (Taken from RBI Website)
C10: 0.0564
C12: Portfolio Annual Return | D12: ='VaR with Optimized Weights '!D12*252 -> 0.32883079
C13: Portfolio SD | D13: ='VaR with Optimized Weights '!D15 -> 0.23394412
C15: Sharpe Ratio | D15: =(D12-C10)/D13 -> 1.1645122
C16: Treynors Ratio | D16: =(D12-D13)/D7 -> 0.54939932
C19: Market Return (NIFTY 500 TRI)
C20: -0.0126
C22: Jensen's Index | D22: =D12- (C10 + D7 * (C20 - C10)) -> 0.28434777

Sheet Analysis and Future
